setup.py
t_objects/__init__.py
t_objects/anonymous_object.py
t_objects.egg-info/PKG-INFO
t_objects.egg-info/SOURCES.txt
t_objects.egg-info/dependency_links.txt
t_objects.egg-info/top_level.txt
t_objects.egg-info/zip-safe