Metadata-Version: 1.0
Name: t-objects
Version: 0.1
Summary: T data structure objects library
Home-page: https://gitlab.com/ddmello/lib/python/t_objects.git
Author: Darrin D'Mello
Author-email: darrin.dmello@gmail.com
License: MIT
Platform: UNKNOWN
